odoo/addons/shopinvader_locomotive_product_seasonality/README.rst
odoo/addons/shopinvader_locomotive_product_seasonality/__init__.py
odoo/addons/shopinvader_locomotive_product_seasonality/__manifest__.py
odoo/addons/shopinvader_locomotive_product_seasonality/components/__init__.py
odoo/addons/shopinvader_locomotive_product_seasonality/components/shopinvader_site_export_mapper.py
odoo/addons/shopinvader_locomotive_product_seasonality/i18n/shopinvader_locomotive_product_seasonality.pot
odoo/addons/shopinvader_locomotive_product_seasonality/readme/CONTRIBUTORS.rst
odoo/addons/shopinvader_locomotive_product_seasonality/readme/DESCRIPTION.rst
odoo/addons/shopinvader_locomotive_product_seasonality/static/description/index.html
odoo/addons/shopinvader_locomotive_product_seasonality/tests/__init__.py
odoo/addons/shopinvader_locomotive_product_seasonality/tests/test_site_settings.py
odoo14_addon_shopinvader_locomotive_product_seasonality-14.0.1.0.1.dist-info/METADATA
odoo14_addon_shopinvader_locomotive_product_seasonality-14.0.1.0.1.dist-info/WHEEL
odoo14_addon_shopinvader_locomotive_product_seasonality-14.0.1.0.1.dist-info/top_level.txt
odoo14_addon_shopinvader_locomotive_product_seasonality-14.0.1.0.1.dist-info/RECORD
